Metadata-Version: 2.1
Name: example-pkg-Ani-Chattaraj
Version: 0.0.1
Summary: Ani is trying his first small example package
Home-page: https://github.com/pypa/sampleproject
Author: Ani Chattaraj
Author-email: chattaraj@uchc.edu
License: UNKNOWN
Platform: UNKNOWN
Classifier: Programming Language :: Python :: 3
Classifier: License :: OSI Approved :: MIT License
Classifier: Operating System :: OS Independent
Requires-Python: >=3.6
